inter_service_sdk/__init__.py
inter_service_sdk/client.py
inter_service_sdk/crypto.py
inter_service_sdk/exceptions.py
inter_service_sdk/server.py
inter_service_sdk/utils.py
inter_service_sdk-1.0.3.dist-info/licenses/LICENSE
inter_service_sdk-1.0.3.dist-info/METADATA
inter_service_sdk-1.0.3.dist-info/WHEEL
inter_service_sdk-1.0.3.dist-info/top_level.txt
inter_service_sdk-1.0.3.dist-info/RECORD
