Metadata-Version: 2.4
Name: inter-service-sdk
Version: 1.0.3
Summary: Complete framework for inter-service communication with client, server utilities, auth and encryption
Home-page: https://github.com/AlexanderRyzhko/inter-service-sdk
Author: Blazel
Author-email: Blazel <dev@blazel.com>
Project-URL: Homepage, https://github.com/AlexanderRyzhko/inter-service-sdk
Project-URL: Bug Tracker, https://github.com/AlexanderRyzhko/inter-service-sdk/issues
Project-URL: Documentation, https://github.com/AlexanderRyzhko/inter-service-sdk#readme
Project-URL: Source Code, https://github.com/AlexanderRyzhko/inter-service-sdk
Keywords: http,client,server,api,rest,fastapi,inter-service,microservices,authentication,encryption,ecc,bearer-token
Classifier: Development Status :: 4 - Beta
Classifier: Intended Audience :: Developers
Classifier: License :: OSI Approved :: MIT License
Classifier: Operating System :: OS Independent
Classifier: Programming Language :: Python :: 3
Classifier: Programming Language :: Python :: 3.8
Classifier: Programming Language :: Python :: 3.9
Classifier: Programming Language :: Python :: 3.10
Classifier: Programming Language :: Python :: 3.11
Classifier: Programming Language :: Python :: 3.12
Classifier: Topic :: Software Development :: Libraries :: Python Modules
Classifier: Topic :: Internet :: WWW/HTTP
Classifier: Topic :: Security :: Cryptography
Requires-Python: >=3.8
License-File: LICENSE
Requires-Dist: requests>=2.31.0
Requires-Dist: fastapi>=0.104.0
Provides-Extra: crypto
Requires-Dist: cryptography>=41.0.0; extra == "crypto"
Provides-Extra: dev
Requires-Dist: pytest>=7.4.0; extra == "dev"
Requires-Dist: pytest-cov>=4.1.0; extra == "dev"
Requires-Dist: pytest-mock>=3.11.1; extra == "dev"
Requires-Dist: requests-mock>=1.11.0; extra == "dev"
Requires-Dist: black>=23.0.0; extra == "dev"
Requires-Dist: flake8>=6.1.0; extra == "dev"
Requires-Dist: mypy>=1.5.0; extra == "dev"
Requires-Dist: types-requests>=2.31.0; extra == "dev"
Requires-Dist: build>=1.0.0; extra == "dev"
Requires-Dist: twine>=4.0.0; extra == "dev"
Requires-Dist: cryptography>=41.0.0; extra == "dev"
Dynamic: author
Dynamic: home-page
Dynamic: license-file
Dynamic: requires-python
